odoo/addons/project_administrator_restricted_visibility/README.rst
odoo/addons/project_administrator_restricted_visibility/__init__.py
odoo/addons/project_administrator_restricted_visibility/__manifest__.py
odoo/addons/project_administrator_restricted_visibility/hooks.py
odoo/addons/project_administrator_restricted_visibility/i18n/it.po
odoo/addons/project_administrator_restricted_visibility/i18n/project_administrator_restricted_visibility.pot
odoo/addons/project_administrator_restricted_visibility/readme/CONFIGURE.rst
odoo/addons/project_administrator_restricted_visibility/readme/CONTRIBUTORS.rst
odoo/addons/project_administrator_restricted_visibility/readme/DESCRIPTION.rst
odoo/addons/project_administrator_restricted_visibility/readme/USAGE.rst
odoo/addons/project_administrator_restricted_visibility/security/project_security.xml
odoo/addons/project_administrator_restricted_visibility/static/description/icon.png
odoo/addons/project_administrator_restricted_visibility/static/description/index.html
odoo/addons/project_administrator_restricted_visibility/tests/__init__.py
odoo/addons/project_administrator_restricted_visibility/tests/test_project_administrator_restricted_visibility.py
odoo13_addon_project_administrator_restricted_visibility-13.0.1.0.1.dev6.dist-info/METADATA
odoo13_addon_project_administrator_restricted_visibility-13.0.1.0.1.dev6.dist-info/WHEEL
odoo13_addon_project_administrator_restricted_visibility-13.0.1.0.1.dev6.dist-info/top_level.txt
odoo13_addon_project_administrator_restricted_visibility-13.0.1.0.1.dev6.dist-info/RECORD
